MANIFEST.in
README.md
setup.cfg
setup.py
datasmash/__init__.py
datasmash/_version.py
datasmash/config.py
datasmash/cylog.py
datasmash/d3m_PFSA_CATEGORICAL_FORCASTER.py
datasmash/d3m_PFSA_FORCASTER.py
datasmash/d3m_cclassification.py
datasmash/d3m_cgclassification.py
datasmash/d3m_classification.py
datasmash/d3m_clustering.py
datasmash/d3m_dataset_loader.py
datasmash/d3m_distance_metric_learning.py
datasmash/d3m_embedding.py
datasmash/d3m_featurization.py
datasmash/d3m_gclassification.py
datasmash/d3m_genesess.py
datasmash/d3m_quantizer.py
datasmash/d3m_xgenesess.py
datasmash/format_d3m_to_zed.py
datasmash/quantizer.py
datasmash/quantizer_old.py
datasmash/uNetworkModels.py
datasmash/utils.py
datasmash/zed_base_classification.py
datasmash/zed_cclassification.py
datasmash/zed_cgclassification.py
datasmash/zed_classification.py
datasmash/zed_clustering.py
datasmash/zed_distance_metric_learning.py
datasmash/zed_embedding.py
datasmash/zed_featurization.py
datasmash/zed_gclassification.py
datasmash/zed_genesess.py
datasmash/zed_xgenesess.py
datasmash.egg-info/PKG-INFO
datasmash.egg-info/SOURCES.txt
datasmash.egg-info/dependency_links.txt
datasmash.egg-info/entry_points.txt
datasmash.egg-info/requires.txt
datasmash.egg-info/top_level.txt
datasmash/bin/Quantizer
datasmash/bin/Quantizer_newer_old
datasmash/bin/Quantizer_old
datasmash/bin/XgenESeSS
datasmash/bin/XgenESeSS_FOR
datasmash/bin/XgenESeSS_cynet
datasmash/bin/corr
datasmash/bin/cynet
datasmash/bin/embed
datasmash/bin/flexroc
datasmash/bin/genESeSS
datasmash/bin/genESeSS_feature
datasmash/bin/json_read
datasmash/bin/proc
datasmash/bin/serializer
datasmash/bin/smash
datasmash/bin/smash_old
datasmash/bin/smashmatch