Metadata-Version: 1.1
Name: datasmash
Version: 0.4.10
Summary: Quantifier of universal similarity amongst arbitrary data streams without a priori knowledge, features, or training.
Home-page: https://gitlab.datadrivendiscovery.org/uchicago/datasmash
Author: Victor Rotaru
Author-email: virotaru@uchicago.edu
License: UNKNOWN
Download-URL: https://gitlab.datadrivendiscovery.org/uchicago/datasmash/archive/0.4.10.tar.gz
Keywords: d3m_primitive
Platform: UNKNOWN
Classifier: Programming Language :: Python :: 3
